{
  "version": "1.1.0",
  "diagrams": [
    {
      "ordinal": 0,
      "scrollPosition": {
        "x": 0,
        "y": 0
      },
      "nodes": [
        {
          "location": {
            "x": 560.72100524772907,
            "y": 429.20756781104012
          },
          "nodeIndex": "dim_usuarios_rls",
          "nodeLineageTag": "eebe675d-be3b-496f-bd80-6128696f11e1",
          "size": {
            "height": 200,
            "width": 234
          },
          "zIndex": 3
        },
        {
          "location": {
            "x": 557,
            "y": 30
          },
          "nodeIndex": "dim_regioes",
          "nodeLineageTag": "77bd2eb4-11f9-4298-8fe4-e6ce013bbf56",
          "size": {
            "height": 200,
            "width": 234
          },
          "zIndex": 1
        },
        {
          "location": {
            "x": 109.54212445852465,
            "y": 0
          },
          "nodeIndex": "fato_bolsa_familia",
          "nodeLineageTag": "7965e709-2ea7-4335-9848-dd9cdb4d4dbe",
          "size": {
            "height": 328,
            "width": 234
          },
          "zIndex": 2
        }
      ],
      "name": "Todas as tabelas",
      "zoomValue": 79.553182037699813,
      "pinKeyFieldsToTop": false,
      "showExtraHeaderInfo": false,
      "hideKeyFieldsWhenCollapsed": false,
      "tablesLocked": false
    }
  ],
  "selectedDiagram": "Todas as tabelas",
  "defaultDiagram": "Todas as tabelas"
}